{"metadata": {"dbt_schema_version": "https://schemas.getdbt.com/dbt/run-results/v6.json", "dbt_version": "1.9.4", "generated_at": "2025-05-25T05:40:13.743286Z", "invocation_id": "6f4b8f4e-7804-4dc0-b303-29390b60d98f", "env": {}}, "results": [{"status": "success", "timing": [{"name": "compile", "started_at": "2025-05-25T05:40:13.680104Z", "completed_at": "2025-05-25T05:40:13.685910Z"}, {"name": "execute", "started_at": "2025-05-25T05:40:13.686092Z", "completed_at": "2025-05-25T05:40:13.686101Z"}], "thread_id": "Thread-1 (worker)", "execution_time": 0.006536960601806641, "adapter_response": {}, "message": null, "failures": null, "unique_id": "model.nyc_parking_violations.bronze_parking_violation_codes", "compiled": true, "compiled_code": "SELECT\n    code AS violation_code,\n    definition,\n    manhattan_96th_st_below,\n    all_other_areas\nFROM\n    parking_violation_codes", "relation_name": "\"nyc_parking_violations\".\"main\".\"bronze_parking_violation_codes\"", "batch_results": null}, {"status": "success", "timing": [{"name": "compile", "started_at": "2025-05-25T05:40:13.686934Z", "completed_at": "2025-05-25T05:40:13.687840Z"}, {"name": "execute", "started_at": "2025-05-25T05:40:13.688001Z", "completed_at": "2025-05-25T05:40:13.688005Z"}], "thread_id": "Thread-1 (worker)", "execution_time": 0.0014390945434570312, "adapter_response": {}, "message": null, "failures": null, "unique_id": "model.nyc_parking_violations.bronze_parking_violations", "compiled": true, "compiled_code": "SELECT\n    summons_number,\n    registration_state,\n    plate_type,\n    issue_date,\n    violation_code,\n    vehicle_body_type,\n    vehicle_make,\n    issuing_agency,\n    vehicle_expiration_date,\n    violation_location,\n    violation_precinct,\n    issuer_precinct,\n    issuer_code,\n    issuer_command,\n    issuer_squad,\n    violation_time,\n    violation_county,\n    violation_legal_code,\n    vehicle_color,\n    vehicle_year,\nFROM\n    parking_violations_2023", "relation_name": "\"nyc_parking_violations\".\"main\".\"bronze_parking_violations\"", "batch_results": null}, {"status": "success", "timing": [{"name": "compile", "started_at": "2025-05-25T05:40:13.688742Z", "completed_at": "2025-05-25T05:40:13.690301Z"}, {"name": "execute", "started_at": "2025-05-25T05:40:13.690587Z", "completed_at": "2025-05-25T05:40:13.690592Z"}], "thread_id": "Thread-1 (worker)", "execution_time": 0.0022079944610595703, "adapter_response": {}, "message": null, "failures": null, "unique_id": "test.nyc_parking_violations.test_placeholder", "compiled": true, "compiled_code": "\n\nWITH this_is_a_test AS (\n    SELECT\n        'this is a test' AS test_value\n)\n\nSELECT\n    test_value\nFROM\n    this_is_a_test\nWHERE\n    test_value != 'this is a test'", "relation_name": "\"nyc_parking_violations\".\"main_dbt_test__audit\".\"test_placeholder\"", "batch_results": null}, {"status": "success", "timing": [{"name": "compile", "started_at": "2025-05-25T05:40:13.691560Z", "completed_at": "2025-05-25T05:40:13.693279Z"}, {"name": "execute", "started_at": "2025-05-25T05:40:13.693442Z", "completed_at": "2025-05-25T05:40:13.693446Z"}], "thread_id": "Thread-1 (worker)", "execution_time": 0.0023539066314697266, "adapter_response": {}, "message": null, "failures": null, "unique_id": "model.nyc_parking_violations.silver_parking_violation_codes", "compiled": true, "compiled_code": "WITH manhattan_violation_codes AS (\n    SELECT\n        violation_code,\n        definition,\n        TRUE AS is_manhattan_96th_st_below,\n        manhattan_96th_st_below AS fee_usd,\n    FROM\n        \"nyc_parking_violations\".\"main\".\"bronze_parking_violation_codes\"\n),\n\nall_other_violation_codes AS (\n    SELECT\n        violation_code,\n        definition,\n        FALSE AS is_manhattan_96th_st_below,\n        all_other_areas AS fee_usd,\n    FROM\n        \"nyc_parking_violations\".\"main\".\"bronze_parking_violation_codes\"\n)\n\nSELECT * FROM manhattan_violation_codes\nUNION ALL\nSELECT * FROM all_other_violation_codes\nORDER BY violation_code ASC", "relation_name": "\"nyc_parking_violations\".\"main\".\"silver_parking_violation_codes\"", "batch_results": null}, {"status": "success", "timing": [{"name": "compile", "started_at": "2025-05-25T05:40:13.694482Z", "completed_at": "2025-05-25T05:40:13.696130Z"}, {"name": "execute", "started_at": "2025-05-25T05:40:13.696332Z", "completed_at": "2025-05-25T05:40:13.696337Z"}], "thread_id": "Thread-1 (worker)", "execution_time": 0.0024788379669189453, "adapter_response": {}, "message": null, "failures": null, "unique_id": "model.nyc_parking_violations.silver_parking_violations", "compiled": true, "compiled_code": "SELECT\n    summons_number,\n    registration_state,\n    plate_type,\n    issue_date,\n    violation_code,\n    vehicle_body_type,\n    vehicle_make,\n    issuing_agency,\n    vehicle_expiration_date,\n    violation_location,\n    violation_precinct,\n    issuer_precinct,\n    issuer_code,\n    issuer_command,\n    issuer_squad,\n    violation_time,\n    violation_county,\n    violation_legal_code,\n    vehicle_color,\n    vehicle_year,\n    CASE WHEN\n        violation_county == 'MN'\n        THEN TRUE\n        ELSE FALSE\n        END AS is_manhattan_96th_st_below\nFROM\n    \"nyc_parking_violations\".\"main\".\"bronze_parking_violations\"", "relation_name": "\"nyc_parking_violations\".\"main\".\"silver_parking_violations\"", "batch_results": null}, {"status": "success", "timing": [{"name": "compile", "started_at": "2025-05-25T05:40:13.697766Z", "completed_at": "2025-05-25T05:40:13.699421Z"}, {"name": "execute", "started_at": "2025-05-25T05:40:13.699598Z", "completed_at": "2025-05-25T05:40:13.699602Z"}], "thread_id": "Thread-1 (worker)", "execution_time": 0.002361774444580078, "adapter_response": {}, "message": null, "failures": null, "unique_id": "model.nyc_parking_violations.silver_violation_tickets", "compiled": true, "compiled_code": "SELECT\n    violations.summons_number,\n    violations.issue_date,\n    violations.violation_code,\n    violations.is_manhattan_96th_st_below,\n    violations.issuing_agency,\n    violations.violation_location,\n    violations.violation_precinct,\n    violations.issuer_precinct,\n    violations.issuer_code,\n    violations.issuer_command,\n    violations.issuer_squad,\n    violations.violation_time,\n    violations.violation_county,\n    violations.violation_legal_code,\n    codes.fee_usd\nFROM\n    \"nyc_parking_violations\".\"main\".\"silver_parking_violations\" AS violations\nLEFT JOIN\n    \"nyc_parking_violations\".\"main\".\"silver_parking_violation_codes\" AS codes ON\n    violations.violation_code = codes.violation_code AND\n    violations.is_manhattan_96th_st_below = codes.is_manhattan_96th_st_below", "relation_name": "\"nyc_parking_violations\".\"main\".\"silver_violation_tickets\"", "batch_results": null}, {"status": "success", "timing": [{"name": "compile", "started_at": "2025-05-25T05:40:13.700723Z", "completed_at": "2025-05-25T05:40:13.702466Z"}, {"name": "execute", "started_at": "2025-05-25T05:40:13.702623Z", "completed_at": "2025-05-25T05:40:13.702627Z"}], "thread_id": "Thread-1 (worker)", "execution_time": 0.0025238990783691406, "adapter_response": {}, "message": null, "failures": null, "unique_id": "model.nyc_parking_violations.silver_violation_vehicles", "compiled": true, "compiled_code": "SELECT\n    summons_number,\n    registration_state,\n    plate_type,\n    vehicle_body_type,\n    vehicle_make,\n    vehicle_expiration_date,\n    vehicle_color,\n    vehicle_year\nFROM\n    \"nyc_parking_violations\".\"main\".\"silver_parking_violations\"", "relation_name": "\"nyc_parking_violations\".\"main\".\"silver_violation_vehicles\"", "batch_results": null}, {"status": "success", "timing": [{"name": "compile", "started_at": "2025-05-25T05:40:13.703664Z", "completed_at": "2025-05-25T05:40:13.705087Z"}, {"name": "execute", "started_at": "2025-05-25T05:40:13.705238Z", "completed_at": "2025-05-25T05:40:13.705241Z"}], "thread_id": "Thread-1 (worker)", "execution_time": 0.0021398067474365234, "adapter_response": {}, "message": null, "failures": null, "unique_id": "model.nyc_parking_violations.silver_valid_violation_tickets", "compiled": true, "compiled_code": "SELECT\n    summons_number,\n    issue_date,\n    violation_code,\n    is_manhattan_96th_st_below,\n    issuing_agency,\n    violation_location,\n    violation_precinct,\n    issuer_precinct,\n    issuer_code,\n    issuer_command,\n    issuer_squad,\n    violation_time,\n    violation_county,\n    fee_usd\nFROM\n    \"nyc_parking_violations\".\"main\".\"silver_violation_tickets\"\nWHERE\n    EXTRACT(year FROM issue_date) == 2023 AND\n    EXTRACT(month FROM issue_date) <= 8", "relation_name": "\"nyc_parking_violations\".\"main\".\"silver_valid_violation_tickets\"", "batch_results": null}, {"status": "success", "timing": [{"name": "compile", "started_at": "2025-05-25T05:40:13.706660Z", "completed_at": "2025-05-25T05:40:13.708586Z"}, {"name": "execute", "started_at": "2025-05-25T05:40:13.708770Z", "completed_at": "2025-05-25T05:40:13.708775Z"}], "thread_id": "Thread-1 (worker)", "execution_time": 0.0026938915252685547, "adapter_response": {}, "message": null, "failures": null, "unique_id": "model.nyc_parking_violations.gold_2023_agency_fee_metrics", "compiled": true, "compiled_code": "WITH recent_agency_fees AS (\n    SELECT\n        silver_valid_violation_tickets.issuing_agency,\n        silver_parking_violation_codes.fee_usd\n    FROM\n        \"nyc_parking_violations\".\"main\".\"silver_valid_violation_tickets\"\n    LEFT JOIN\n        \"nyc_parking_violations\".\"main\".\"silver_parking_violation_codes\" AS silver_parking_violation_codes ON\n            silver_valid_violation_tickets.violation_code = silver_parking_violation_codes.violation_code AND\n            silver_valid_violation_tickets.is_manhattan_96th_st_below = silver_parking_violation_codes.is_manhattan_96th_st_below\n    WHERE\n        silver_valid_violation_tickets.issue_date >= (SELECT MAX(issue_date) - INTERVAL '90 days' FROM \"nyc_parking_violations\".\"main\".\"silver_valid_violation_tickets\")\n)\n\nSELECT\n    issuing_agency,\n    SUM(fee_usd) AS total_ticket_fees_usd,\n    AVG(fee_usd) AS average_fee_usd,\n    COUNT(*) AS ticket_count\nFROM\n    recent_agency_fees\nGROUP BY\n    issuing_agency\nORDER BY\n    ticket_count DESC", "relation_name": "\"nyc_parking_violations\".\"main\".\"gold_2023_agency_fee_metrics\"", "batch_results": null}, {"status": "success", "timing": [{"name": "compile", "started_at": "2025-05-25T05:40:13.709801Z", "completed_at": "2025-05-25T05:40:13.711946Z"}, {"name": "execute", "started_at": "2025-05-25T05:40:13.712146Z", "completed_at": "2025-05-25T05:40:13.712151Z"}], "thread_id": "Thread-1 (worker)", "execution_time": 0.002886056900024414, "adapter_response": {}, "message": null, "failures": null, "unique_id": "model.nyc_parking_violations.gold_2023_county_violations_day_of_week_heatmap", "compiled": true, "compiled_code": "WITH tickets_by_county AS (\n    SELECT\n        violation_county,\n        CAST(SUM(CASE WHEN EXTRACT(dow FROM issue_date) = 0 THEN 1 ELSE 0 END) AS INTEGER) AS sunday,\n        CAST(SUM(CASE WHEN EXTRACT(dow FROM issue_date) = 1 THEN 1 ELSE 0 END) AS INTEGER) AS monday,\n        CAST(SUM(CASE WHEN EXTRACT(dow FROM issue_date) = 2 THEN 1 ELSE 0 END) AS INTEGER) AS tuesday,\n        CAST(SUM(CASE WHEN EXTRACT(dow FROM issue_date) = 3 THEN 1 ELSE 0 END) AS INTEGER) AS wednesday,\n        CAST(SUM(CASE WHEN EXTRACT(dow FROM issue_date) = 4 THEN 1 ELSE 0 END) AS INTEGER) AS thursday,\n        CAST(SUM(CASE WHEN EXTRACT(dow FROM issue_date) = 5 THEN 1 ELSE 0 END) AS INTEGER) AS friday,\n        CAST(SUM(CASE WHEN EXTRACT(dow FROM issue_date) = 6 THEN 1 ELSE 0 END) AS INTEGER) AS saturday\n    FROM\n        \"nyc_parking_violations\".\"main\".\"silver_valid_violation_tickets\"\n    WHERE\n        issue_date >= (SELECT MAX(issue_date) - INTERVAL '365 days' FROM \"nyc_parking_violations\".\"main\".\"silver_valid_violation_tickets\")\n    GROUP BY\n        violation_county\n)\n\nSELECT\n    violation_county,\n    sunday,\n    monday,\n    tuesday,\n    wednesday,\n    thursday,\n    friday,\n    saturday,\n    (sunday + monday + tuesday + wednesday + thursday + friday + saturday) AS total_tickets\nFROM\n    tickets_by_county\nORDER BY\n    tickets_by_county DESC", "relation_name": "\"nyc_parking_violations\".\"main\".\"gold_2023_county_violations_day_of_week_heatmap\"", "batch_results": null}, {"status": "success", "timing": [{"name": "compile", "started_at": "2025-05-25T05:40:13.713048Z", "completed_at": "2025-05-25T05:40:13.714764Z"}, {"name": "execute", "started_at": "2025-05-25T05:40:13.714971Z", "completed_at": "2025-05-25T05:40:13.714976Z"}], "thread_id": "Thread-1 (worker)", "execution_time": 0.002377033233642578, "adapter_response": {}, "message": null, "failures": null, "unique_id": "model.nyc_parking_violations.gold_2023_ticket_counts_year_month", "compiled": true, "compiled_code": "WITH year_month_tickets AS (\n    SELECT\n        EXTRACT(year FROM issue_date) AS violation_year,\n        EXTRACT(month FROM issue_date) AS violation_month,\n        COUNT(*) AS ticket_count\n    FROM\n        \"nyc_parking_violations\".\"main\".\"silver_valid_violation_tickets\"\n    GROUP BY\n        violation_year,\n        violation_month\n),\n\nprevious_month_comparison AS (\n    SELECT\n        violation_year,\n        violation_month,\n        ticket_count,\n        LAG(ticket_count) OVER (ORDER BY violation_year, violation_month) AS previous_month_ticket_count,\n        CAST(violation_year AS VARCHAR) || '-' || LPAD(CAST(violation_month AS VARCHAR), 2, '0') AS year_month\n    FROM\n        year_month_tickets\n)\n\nSELECT\n    year_month,\n    ticket_count,\n    previous_month_ticket_count,\n    ticket_count - previous_month_ticket_count AS monthly_change,\n    CASE\n        WHEN previous_month_ticket_count IS NULL THEN NULL\n        ELSE ROUND((ticket_count - previous_month_ticket_count) * 100.0 / previous_month_ticket_count, 1)\n    END AS percent_change\nFROM\n    previous_month_comparison\nORDER BY\n    violation_year DESC,\n    violation_month DESC", "relation_name": "\"nyc_parking_violations\".\"main\".\"gold_2023_ticket_counts_year_month\"", "batch_results": null}, {"status": "success", "timing": [{"name": "compile", "started_at": "2025-05-25T05:40:13.716125Z", "completed_at": "2025-05-25T05:40:13.717809Z"}, {"name": "execute", "started_at": "2025-05-25T05:40:13.717995Z", "completed_at": "2025-05-25T05:40:13.718000Z"}], "thread_id": "Thread-1 (worker)", "execution_time": 0.002410888671875, "adapter_response": {}, "message": null, "failures": null, "unique_id": "model.nyc_parking_violations.gold_2023_ticket_counts_year_week", "compiled": true, "compiled_code": "WITH year_week_tickets AS (\n    SELECT\n        EXTRACT(year FROM issue_date) AS violation_year,\n        EXTRACT(week FROM issue_date) AS week_of_year,\n        COUNT(*) AS ticket_count\n    FROM\n        \"nyc_parking_violations\".\"main\".\"silver_valid_violation_tickets\"\n    GROUP BY\n        violation_year,\n        week_of_year\n),\n\nprevious_week_comparison AS (\n    SELECT\n        violation_year,\n        week_of_year,\n        ticket_count,\n        LAG(ticket_count) OVER (ORDER BY week_of_year) AS previous_week_ticket_count,\n        CAST(violation_year AS VARCHAR) || '-W' || LPAD(CAST(week_of_year AS VARCHAR), 2, '0') AS year_week\n    FROM\n        year_week_tickets\n)\n\nSELECT\n    year_week,\n    ticket_count,\n    previous_week_ticket_count,\n    ticket_count - previous_week_ticket_count AS weekly_change,\n    CASE\n        WHEN previous_week_ticket_count IS NULL THEN NULL\n        ELSE ROUND((ticket_count - previous_week_ticket_count) * 100.0 / previous_week_ticket_count, 1)\n    END AS percent_change\nFROM\n    previous_week_comparison\nORDER BY\n    violation_year DESC,\n    week_of_year DESC", "relation_name": "\"nyc_parking_violations\".\"main\".\"gold_2023_ticket_counts_year_week\"", "batch_results": null}, {"status": "success", "timing": [{"name": "compile", "started_at": "2025-05-25T05:40:13.718909Z", "completed_at": "2025-05-25T05:40:13.720881Z"}, {"name": "execute", "started_at": "2025-05-25T05:40:13.721068Z", "completed_at": "2025-05-25T05:40:13.721072Z"}], "thread_id": "Thread-1 (worker)", "execution_time": 0.002638101577758789, "adapter_response": {}, "message": null, "failures": null, "unique_id": "model.nyc_parking_violations.gold_2023_violations_day_of_week_heatmap", "compiled": true, "compiled_code": "WITH tickets_by_violation AS (\n    SELECT\n        silver_valid_violation_tickets.violation_code,\n        silver_parking_violation_codes.definition AS violation_definition,\n        CAST(SUM(CASE WHEN EXTRACT(dow FROM issue_date) = 0 THEN 1 ELSE 0 END) AS INTEGER) AS sunday,\n        CAST(SUM(CASE WHEN EXTRACT(dow FROM issue_date) = 1 THEN 1 ELSE 0 END) AS INTEGER) AS monday,\n        CAST(SUM(CASE WHEN EXTRACT(dow FROM issue_date) = 2 THEN 1 ELSE 0 END) AS INTEGER) AS tuesday,\n        CAST(SUM(CASE WHEN EXTRACT(dow FROM issue_date) = 3 THEN 1 ELSE 0 END) AS INTEGER) AS wednesday,\n        CAST(SUM(CASE WHEN EXTRACT(dow FROM issue_date) = 4 THEN 1 ELSE 0 END) AS INTEGER) AS thursday,\n        CAST(SUM(CASE WHEN EXTRACT(dow FROM issue_date) = 5 THEN 1 ELSE 0 END) AS INTEGER) AS friday,\n        CAST(SUM(CASE WHEN EXTRACT(dow FROM issue_date) = 6 THEN 1 ELSE 0 END) AS INTEGER) AS saturday\n    FROM\n        \"nyc_parking_violations\".\"main\".\"silver_valid_violation_tickets\"\n    LEFT JOIN\n        \"nyc_parking_violations\".\"main\".\"silver_parking_violation_codes\" AS silver_parking_violation_codes ON\n            silver_valid_violation_tickets.violation_code = silver_parking_violation_codes.violation_code AND\n            silver_valid_violation_tickets.is_manhattan_96th_st_below = silver_parking_violation_codes.is_manhattan_96th_st_below\n    WHERE\n        issue_date >= (SELECT MAX(issue_date) - INTERVAL '365 days' FROM silver_valid_violation_tickets)\n    GROUP BY\n        silver_valid_violation_tickets.violation_code,\n        violation_definition\n)\n\nSELECT\n    violation_code,\n    violation_definition,\n    sunday,\n    monday,\n    tuesday,\n    wednesday,\n    thursday,\n    friday,\n    saturday,\n    (sunday + monday + tuesday + wednesday + thursday + friday + saturday) AS total_tickets\nFROM\n    tickets_by_violation\nORDER BY\n    total_tickets DESC", "relation_name": "\"nyc_parking_violations\".\"main\".\"gold_2023_violations_day_of_week_heatmap\"", "batch_results": null}, {"status": "success", "timing": [{"name": "compile", "started_at": "2025-05-25T05:40:13.722174Z", "completed_at": "2025-05-25T05:40:13.723985Z"}, {"name": "execute", "started_at": "2025-05-25T05:40:13.724250Z", "completed_at": "2025-05-25T05:40:13.724254Z"}], "thread_id": "Thread-1 (worker)", "execution_time": 0.0026259422302246094, "adapter_response": {}, "message": null, "failures": null, "unique_id": "model.nyc_parking_violations.gold_2023_weekly_violations_day_of_week_heatmap", "compiled": true, "compiled_code": "WITH tickets_by_weekday AS (\n    SELECT\n        CAST(EXTRACT(year FROM issue_date) AS VARCHAR) || '-W' || LPAD(CAST(EXTRACT(week FROM issue_date) AS VARCHAR), 2, '0') AS year_week,\n        CAST(SUM(CASE WHEN EXTRACT(dow FROM issue_date) = 0 THEN 1 ELSE 0 END) AS INTEGER) AS sunday,\n        CAST(SUM(CASE WHEN EXTRACT(dow FROM issue_date) = 1 THEN 1 ELSE 0 END) AS INTEGER) AS monday,\n        CAST(SUM(CASE WHEN EXTRACT(dow FROM issue_date) = 2 THEN 1 ELSE 0 END) AS INTEGER) AS tuesday,\n        CAST(SUM(CASE WHEN EXTRACT(dow FROM issue_date) = 3 THEN 1 ELSE 0 END) AS INTEGER) AS wednesday,\n        CAST(SUM(CASE WHEN EXTRACT(dow FROM issue_date) = 4 THEN 1 ELSE 0 END) AS INTEGER) AS thursday,\n        CAST(SUM(CASE WHEN EXTRACT(dow FROM issue_date) = 5 THEN 1 ELSE 0 END) AS INTEGER) AS friday,\n        CAST(SUM(CASE WHEN EXTRACT(dow FROM issue_date) = 6 THEN 1 ELSE 0 END) AS INTEGER) AS saturday\n    FROM\n        \"nyc_parking_violations\".\"main\".\"silver_valid_violation_tickets\"\n    WHERE\n        issue_date >= (SELECT MAX(issue_date) - INTERVAL '365 days' FROM \"nyc_parking_violations\".\"main\".\"silver_valid_violation_tickets\")\n    GROUP BY\n        year_week\n)\n\nSELECT\n    year_week,\n    sunday,\n    monday,\n    tuesday,\n    wednesday,\n    thursday,\n    friday,\n    saturday\nFROM\n    tickets_by_weekday\nORDER BY\n    year_week DESC", "relation_name": "\"nyc_parking_violations\".\"main\".\"gold_2023_weekly_violations_day_of_week_heatmap\"", "batch_results": null}, {"status": "success", "timing": [{"name": "compile", "started_at": "2025-05-25T05:40:13.725045Z", "completed_at": "2025-05-25T05:40:13.726491Z"}, {"name": "execute", "started_at": "2025-05-25T05:40:13.726639Z", "completed_at": "2025-05-25T05:40:13.726642Z"}], "thread_id": "Thread-1 (worker)", "execution_time": 0.001940011978149414, "adapter_response": {}, "message": null, "failures": null, "unique_id": "model.nyc_parking_violations.gold_latest_tickets_90_days", "compiled": true, "compiled_code": "SELECT\n    summons_number,\n    issue_date,\n    violation_code,\n    is_manhattan_96th_st_below,\n    issuing_agency,\n    violation_location,\n    violation_precinct,\n    issuer_precinct,\n    issuer_code,\n    issuer_command,\n    issuer_squad,\n    violation_time,\n    violation_county,\n    fee_usd\nFROM\n    \"nyc_parking_violations\".\"main\".\"silver_valid_violation_tickets\"\nWHERE\n    issue_date >= (SELECT MAX(issue_date) - INTERVAL '90 days' FROM \"nyc_parking_violations\".\"main\".\"silver_valid_violation_tickets\")\nORDER BY\n    issue_date DESC", "relation_name": "\"nyc_parking_violations\".\"main\".\"gold_latest_tickets_90_days\"", "batch_results": null}, {"status": "success", "timing": [{"name": "compile", "started_at": "2025-05-25T05:40:13.727584Z", "completed_at": "2025-05-25T05:40:13.729856Z"}, {"name": "execute", "started_at": "2025-05-25T05:40:13.730062Z", "completed_at": "2025-05-25T05:40:13.730067Z"}], "thread_id": "Thread-1 (worker)", "execution_time": 0.0030357837677001953, "adapter_response": {}, "message": null, "failures": null, "unique_id": "model.nyc_parking_violations.gold_precinct_ticket_fee_sum_90_days", "compiled": true, "compiled_code": "WITH precinct_fees AS (\n    SELECT\n        silver_valid_violation_tickets.issuer_precinct,\n        silver_parking_violation_codes.fee_usd\n    FROM\n        \"nyc_parking_violations\".\"main\".\"silver_valid_violation_tickets\"\n    LEFT JOIN\n        \"nyc_parking_violations\".\"main\".\"silver_parking_violation_codes\" AS silver_parking_violation_codes ON\n            silver_valid_violation_tickets.violation_code = silver_parking_violation_codes.violation_code AND\n            silver_valid_violation_tickets.is_manhattan_96th_st_below = silver_parking_violation_codes.is_manhattan_96th_st_below\n    WHERE\n        silver_valid_violation_tickets.issue_date >= (SELECT MAX(issue_date) - INTERVAL '90 days' FROM \"nyc_parking_violations\".\"main\".\"silver_valid_violation_tickets\")\n)\n\nSELECT\n    issuer_precinct,\n    SUM(fee_usd) AS total_ticket_fees_usd\nFROM\n    precinct_fees\nGROUP BY\n    issuer_precinct\nORDER BY\n    total_ticket_fees_usd DESC", "relation_name": "\"nyc_parking_violations\".\"main\".\"gold_precinct_ticket_fee_sum_90_days\"", "batch_results": null}, {"status": "success", "timing": [{"name": "compile", "started_at": "2025-05-25T05:40:13.730977Z", "completed_at": "2025-05-25T05:40:13.732660Z"}, {"name": "execute", "started_at": "2025-05-25T05:40:13.732829Z", "completed_at": "2025-05-25T05:40:13.732832Z"}], "thread_id": "Thread-1 (worker)", "execution_time": 0.002257823944091797, "adapter_response": {}, "message": null, "failures": null, "unique_id": "model.nyc_parking_violations.gold_tickets_by_agency_90_days", "compiled": true, "compiled_code": "SELECT\n    issuing_agency,\n    COUNT(*) AS ticket_count\nFROM\n    \"nyc_parking_violations\".\"main\".\"silver_valid_violation_tickets\"\nWHERE\n    issue_date >= (SELECT MAX(issue_date) - INTERVAL '90 days' FROM \"nyc_parking_violations\".\"main\".\"silver_valid_violation_tickets\")\nGROUP BY\n    issuing_agency\nORDER BY\n    ticket_count DESC", "relation_name": "\"nyc_parking_violations\".\"main\".\"gold_tickets_by_agency_90_days\"", "batch_results": null}, {"status": "success", "timing": [{"name": "compile", "started_at": "2025-05-25T05:40:13.733883Z", "completed_at": "2025-05-25T05:40:13.735552Z"}, {"name": "execute", "started_at": "2025-05-25T05:40:13.735717Z", "completed_at": "2025-05-25T05:40:13.735720Z"}], "thread_id": "Thread-1 (worker)", "execution_time": 0.0024483203887939453, "adapter_response": {}, "message": null, "failures": null, "unique_id": "model.nyc_parking_violations.gold_tickets_by_county_90_days", "compiled": true, "compiled_code": "SELECT\n    violation_county,\n    COUNT(*) AS ticket_count\nFROM\n    \"nyc_parking_violations\".\"main\".\"silver_valid_violation_tickets\"\nWHERE\n    issue_date >= (SELECT MAX(issue_date) - INTERVAL '90 days' FROM \"nyc_parking_violations\".\"main\".\"silver_valid_violation_tickets\")\nGROUP BY\n    violation_county\nORDER BY\n    ticket_count DESC", "relation_name": "\"nyc_parking_violations\".\"main\".\"gold_tickets_by_county_90_days\"", "batch_results": null}, {"status": "success", "timing": [{"name": "compile", "started_at": "2025-05-25T05:40:13.736666Z", "completed_at": "2025-05-25T05:40:13.738951Z"}, {"name": "execute", "started_at": "2025-05-25T05:40:13.739220Z", "completed_at": "2025-05-25T05:40:13.739226Z"}], "thread_id": "Thread-1 (worker)", "execution_time": 0.003130674362182617, "adapter_response": {}, "message": null, "failures": null, "unique_id": "model.nyc_parking_violations.gold_tickets_by_vehicle_90_days", "compiled": true, "compiled_code": "WITH valid_vehicle_tickets AS (\n    SELECT\n        silver_valid_violation_tickets.summons_number,\n        silver_violation_vehicles.vehicle_make,\n        silver_violation_vehicles.plate_type,\n        silver_violation_vehicles.registration_state\n    FROM\n        \"nyc_parking_violations\".\"main\".\"silver_valid_violation_tickets\"\n    INNER JOIN\n        \"nyc_parking_violations\".\"main\".\"silver_violation_vehicles\"\n        ON silver_valid_violation_tickets.summons_number = silver_violation_vehicles.summons_number\n    WHERE\n        silver_valid_violation_tickets.issue_date >= (SELECT MAX(issue_date) - INTERVAL '90 days' FROM \"nyc_parking_violations\".\"main\".\"silver_valid_violation_tickets\")\n)\n\nSELECT\n    vehicle_make,\n    plate_type,\n    registration_state,\n    COUNT(*) AS ticket_count\nFROM\n    valid_vehicle_tickets\nGROUP BY\n    vehicle_make,\n    plate_type,\n    registration_state\nORDER BY\n    ticket_count DESC", "relation_name": "\"nyc_parking_violations\".\"main\".\"gold_tickets_by_vehicle_90_days\"", "batch_results": null}, {"status": "success", "timing": [{"name": "compile", "started_at": "2025-05-25T05:40:13.740196Z", "completed_at": "2025-05-25T05:40:13.741950Z"}, {"name": "execute", "started_at": "2025-05-25T05:40:13.742110Z", "completed_at": "2025-05-25T05:40:13.742113Z"}], "thread_id": "Thread-1 (worker)", "execution_time": 0.002385854721069336, "adapter_response": {}, "message": null, "failures": null, "unique_id": "model.nyc_parking_violations.gold_tickets_by_violation_90_days", "compiled": true, "compiled_code": "SELECT\n    silver_valid_violation_tickets.violation_code,\n    silver_parking_violation_codes.definition AS violation_definition,\n    COUNT(*) AS ticket_count\nFROM\n    \"nyc_parking_violations\".\"main\".\"silver_valid_violation_tickets\"\nLEFT JOIN\n    \"nyc_parking_violations\".\"main\".\"silver_parking_violation_codes\" AS silver_parking_violation_codes ON\n        silver_valid_violation_tickets.violation_code = silver_parking_violation_codes.violation_code AND\n        silver_valid_violation_tickets.is_manhattan_96th_st_below = silver_parking_violation_codes.is_manhattan_96th_st_below\nWHERE\n    silver_valid_violation_tickets.issue_date >= (SELECT MAX(issue_date) - INTERVAL '90 days' FROM \"nyc_parking_violations\".\"main\".\"silver_valid_violation_tickets\")\nGROUP BY\n    silver_valid_violation_tickets.violation_code,\n    silver_parking_violation_codes.definition\nORDER BY\n    ticket_count DESC", "relation_name": "\"nyc_parking_violations\".\"main\".\"gold_tickets_by_violation_90_days\"", "batch_results": null}], "elapsed_time": 0.12660670280456543, "args": {"static": false, "write_json": true, "exclude": [], "project_dir": "/Users/onthemarkdata/repos/github/data-quality-analytics-and-serving-3918208/nyc_parking_violations", "favor_state": false, "which": "generate", "introspect": true, "cache_selected_only": false, "print": true, "require_resource_names_without_spaces": false, "warn_error_options": {"include": [], "exclude": []}, "indirect_selection": "eager", "log_file_max_bytes": 10485760, "static_parser": true, "state_modified_compare_more_unrendered_values": false, "log_level": "info", "printer_width": 80, "partial_parse_file_diff": true, "log_level_file": "debug", "log_format_file": "debug", "invocation_command": "dbt docs generate", "strict_mode": false, "show_resource_report": false, "log_path": "/Users/onthemarkdata/repos/github/data-quality-analytics-and-serving-3918208/nyc_parking_violations/logs", "send_anonymous_usage_stats": true, "macro_debugging": false, "require_batched_execution_for_custom_microbatch_strategy": false, "compile": true, "version_check": true, "use_colors_file": true, "require_explicit_package_overrides_for_builtin_materializations": true, "partial_parse": true, "populate_cache": true, "profiles_dir": "/Users/onthemarkdata/repos/github/data-quality-analytics-and-serving-3918208/nyc_parking_violations", "log_format": "default", "require_yaml_configuration_for_mf_time_spines": false, "require_nested_cumulative_type_params": false, "select": [], "empty_catalog": false, "defer": false, "source_freshness_run_project_hooks": false, "vars": {}, "state_modified_compare_vars": false, "use_colors": true, "quiet": false, "skip_nodes_if_on_run_start_fails": false}}